m2io_tmp-0.1.3.dist-info/METADATA
m2io_tmp-0.1.3.dist-info/WHEEL
m2io_tmp-0.1.3.dist-info/licenses/LICENSE
m2io_tmp/__init__.py
m2io_tmp/m2io_tmp.cpython-311-powerpc64le-linux-gnu.so
m2io_tmp-0.1.3.dist-info/RECORD
