Metadata-Version: 2.3
Name: m2io_tmp
Version: 0.1.3
Classifier: Programming Language :: Rust
Classifier: Programming Language :: Python :: Implementation :: CPython
Classifier: Programming Language :: Python :: Implementation :: PyPy
License-File: LICENSE
License: EUPL-1.2
Requires-Python: >=3.8
